pyjamas/LICENSE
pyjamas/__init__.py
pyjamas/default_config.toml
pyjamas/dragdropmainwindow.py
pyjamas/orthogonalviewswindow.py
pyjamas/pjscore.py
pyjamas/pjseventfilter.py
pyjamas/pjsthreads.py
pyjamas/pyjamas.tif
pyjamas/rutils.py
pyjamas/version.py
pyjamas/dialogs/__init__.py
pyjamas/dialogs/adjustcontrast.py
pyjamas/dialogs/batchanalysis.py
pyjamas/dialogs/batchflatfield.py
pyjamas/dialogs/batchprojectconcat.py
pyjamas/dialogs/batchresize.py
pyjamas/dialogs/classifierdialogABC.py
pyjamas/dialogs/classifiertype.py
pyjamas/dialogs/configurekeybindingsdialog.py
pyjamas/dialogs/dropdowndialog.py
pyjamas/dialogs/expandnpropagateseeds.py
pyjamas/dialogs/expandseeds.py
pyjamas/dialogs/findpuncta.py
pyjamas/dialogs/findseeds.py
pyjamas/dialogs/footprintdialog.py
pyjamas/dialogs/logregression.py
pyjamas/dialogs/matplotlibdialog.py
pyjamas/dialogs/measurepoly.py
pyjamas/dialogs/neuralnet.py
pyjamas/dialogs/nonmax_suppr.py
pyjamas/dialogs/propagateseeds.py
pyjamas/dialogs/rescuneuralnet.py
pyjamas/dialogs/svm.py
pyjamas/dialogs/textdialog.py
pyjamas/dialogs/texteditdialog.py
pyjamas/dialogs/timepoints.py
pyjamas/external/__init__.py
pyjamas/external/pascal_voc_io.py
pyjamas/notebooks/quickienet.ipynb
pyjamas/notebooks/rescunet.ipynb
pyjamas/notebooks/unet.ipynb
pyjamas/plugins/heterogeneity/heterogeneity.py
pyjamas/plugins/sampleplugin/sampleplugin.py
pyjamas/plugins/samplepluginpackage/samplepluginpackage.py
pyjamas/rannotations/__init__.py
pyjamas/rannotations/rannotation.py
pyjamas/rannotations/rpolyline.py
pyjamas/rannotations/rvector2d.py
pyjamas/rcallbacks/__init__.py
pyjamas/rcallbacks/rcallback.py
pyjamas/rcallbacks/rcbabout.py
pyjamas/rcallbacks/rcbannotations.py
pyjamas/rcallbacks/rcbbatchprocess.py
pyjamas/rcallbacks/rcbclassifiers.py
pyjamas/rcallbacks/rcbimage.py
pyjamas/rcallbacks/rcbio.py
pyjamas/rcallbacks/rcbmeasure.py
pyjamas/rcallbacks/rcboptions.py
pyjamas/rcallbacks/rcbplugins.py
pyjamas/rimage/__init__.py
pyjamas/rimage/csgraph.py
pyjamas_rfglab-2026.1.2.dist-info/METADATA
pyjamas_rfglab-2026.1.2.dist-info/WHEEL
pyjamas_rfglab-2026.1.2.dist-info/entry_points.txt
pyjamas_rfglab-2026.1.2.dist-info/top_level.txt
pyjamas_rfglab-2026.1.2.dist-info/RECORD
