Metadata-Version: 2.4
Name: pyjamas-rfglab
Version: 2026.1.2
Summary: PyJAMAS is Just A More Awesome SIESTA
Author-email: Rodrigo Fernandez-Gonzalez <rodrigo.fernandez.gonzalez@utoronto.ca>
License: GPL-3.0-or-later
Classifier: Programming Language :: Python
Classifier: Programming Language :: Python :: 3
Classifier: Programming Language :: Python :: 3.10
Classifier: Programming Language :: Python :: 3.11
Classifier: Programming Language :: Python :: 3.12
Classifier: Programming Language :: Python :: 3.13
Classifier: License :: OSI Approved :: GNU General Public License v3 (GPLv3)
Classifier: Operating System :: OS Independent
Requires-Python: <=3.13,>=3.10
Requires-Dist: ipywidgets>=8.0.4
Requires-Dist: joblib>=1.2.0
Requires-Dist: lxml>=4.9.2
Requires-Dist: keras>=3.12.0
Requires-Dist: matplotlib>=3.7.1
Requires-Dist: nbformat>=5.7.0
Requires-Dist: networkx>=2.8.4
Requires-Dist: nbformat==5.10.4
Requires-Dist: numba==0.62.1
Requires-Dist: numpy==2.2.6
Requires-Dist: opencv-python-headless==4.12.0.88
Requires-Dist: pandas==2.3.3
Requires-Dist: pyqt6==6.8.0
Requires-Dist: scikit-image>=0.25.0
Requires-Dist: scikit-learn>=1.2.2
Requires-Dist: scipy>=1.10.1
Requires-Dist: seaborn>=0.13.0
Requires-Dist: setuptools>=67.8.0
Requires-Dist: shapely>=2.0.1
Requires-Dist: tensorboard>=2.20.0
Requires-Dist: tomlkit>=0.13.0
Requires-Dist: torch==2.9.1; os_name == "posix"
Requires-Dist: torch==2.8.0; os_name == "nt"
Requires-Dist: tqdm==4.67.1
